aperture/__init__.py
aperture/__main__.py
aperture/config_file.py
aperture/errors.py
aperture/options.py
aperture/commands/__init__.py
aperture/commands/aperture.py
aperture/commands/command.py
aperture/util/__init__.py
aperture/util/directories.py
aperture/util/files.py
aperture/util/output.py
aperture_cli-1.0.0.dist-info/METADATA
aperture_cli-1.0.0.dist-info/RECORD
aperture_cli-1.0.0.dist-info/WHEEL
aperture_cli-1.0.0.dist-info/entry_points.txt
aperture_cli-1.0.0.dist-info/top_level.txt
