Metadata-Version: 2.1
Name: aperture-cli
Version: 1.0.0
Summary: An image re-sizing and compression tool
Home-page: https://github.com/Aperture-py/aperture
Author: salvatorej1@wit.edu, kennedyd3@wit.edu, robbinsa@wit.edu
Author-email: UNKNOWN
License: MIT License
Requires-Dist: docopt
Requires-Dist: aperturelib
